reportXlsx/__init__.py
reportXlsx/to_excel.py
reportXlsx/resources/linux/SkiaSharp.dll
reportXlsx/resources/linux/Spire.XLS.dll
reportXlsx/resources/windows/Spire.XLS.dll
reportXlsx-9.3.2.dist-info/METADATA
reportXlsx-9.3.2.dist-info/WHEEL
reportXlsx-9.3.2.dist-info/top_level.txt
reportXlsx-9.3.2.dist-info/RECORD
