Metadata-Version: 2.1
Name: reportXlsx
Version: 9.3.2
Summary: 这是一个操作xlsx的库,兼容windows和linux
Home-page: https://github.com/bailulue
Author: bailu
Author-email: yabailu@chinatelecom.cn
License: UNKNOWN
Platform: UNKNOWN
Requires-Dist: pandas
Requires-Dist: openpyxl
Requires-Dist: pythonnet
Requires-Dist: xlwings
